{
  "tipoComercializacion": {
    "bc": {
      "text": "Tipos de Comercialización",
      "link": "/scv/tipocomercializacion"
    },
    "consulta": {
        "title": "Administración de Tipo de Comercialización",
        "grid": {
            "headers": {
                "clave": "Clave",
              "nombre": "Nombre",
               "paquete":  "Paquete",
                "estatus": "Estatus"
            }
        }
    },
    "editar": {
      "title": "Modificar Tipo de Comercialización"
    },
    "form": {
      "ID": {
        "label": "Clave",
        "helpLabel": "Capture la Clave",
        "validaciones": {
          "requerida": "La clave es requerida"
        }
      },
      "Nombre": {
        "label": "Nombre",
        "helpLabel": "Capture el nombre",
        "validaciones": {
          "requerida": "El nombre es requerido."
        }
      },
      "Clave": {
        "label": "Clave",
        "helpLabel": "Capture la Clave",
        "validaciones": {
          "requerida": "La clave es requerida"
        }
      },
      "Paquete": {
        "label": "Paquete",
        "helpLabel": "Paquete"
      },
      "Estatus": {
        "label": "Activo",
        "helpLabel": "Estatus"
      }
    },
    "mensajes": {
      "exito": "El Tipo de Comercialización ha sido actualizada"
    },
    "titulo": {
      "nuevo": "Nueva Tipo de Comercialización"
    }
  }
}